jirafs/.pre-commit-config.yaml
jirafs/__init__.py
jirafs/cmdline.py
jirafs/constants.py
jirafs/exceptions.py
jirafs/jirafieldmanager.py
jirafs/jiralinkmanager.py
jirafs/migrations.py
jirafs/plugin.py
jirafs/readers.py
jirafs/ticketfolder.py
jirafs/types.py
jirafs/utils.py
jirafs/commands/__init__.py
jirafs/commands/assign.py
jirafs/commands/clone.py
jirafs/commands/commit.py
jirafs/commands/config.py
jirafs/commands/create.py
jirafs/commands/debug.py
jirafs/commands/diff.py
jirafs/commands/fetch.py
jirafs/commands/field.py
jirafs/commands/git.py
jirafs/commands/log.py
jirafs/commands/match.py
jirafs/commands/merge.py
jirafs/commands/open.py
jirafs/commands/plugins.py
jirafs/commands/pull.py
jirafs/commands/push.py
jirafs/commands/search_users.py
jirafs/commands/setfield.py
jirafs/commands/status.py
jirafs/commands/submit.py
jirafs/commands/subtask.py
jirafs/commands/transition.py
jirafs/commands/version.py
jirafs/commands/preview/__init__.py
jirafs/commands/preview/templates/base.html
jirafs/commands/preview/templates/traceback.html
jirafs-2.3.1.dist-info/LICENSE
jirafs-2.3.1.dist-info/METADATA
jirafs-2.3.1.dist-info/WHEEL
jirafs-2.3.1.dist-info/entry_points.txt
jirafs-2.3.1.dist-info/top_level.txt
jirafs-2.3.1.dist-info/RECORD
