Metadata-Version: 2.1
Name: jirafs
Version: 2.3.1
Summary: Edit Jira issues as text files locally.
Home-page: https://github.com/coddingtonbear/jirafs
Author: Adam Coddington
Author-email: me@adamcoddington.net
License: UNKNOWN
Platform: UNKNOWN
Classifier: License :: OSI Approved :: MIT License
Classifier: Operating System :: OS Independent
Classifier: Programming Language :: Python :: 3
License-File: LICENSE
Requires-Dist: blessings (<2.0,>=1.5.1)
Requires-Dist: environmental-override (<1.0.0,>=0.1.2)
Requires-Dist: jinja2 (<3.0,>=2.10.3)
Requires-Dist: jira (<4,>=3.1.1)
Requires-Dist: prettytable (<1.0,>=0.7.2)
Requires-Dist: python-dateutil (<3,>=2.8.1)
Requires-Dist: watchdog (<1.0.0,>=0.9.0)
